trame/__init__.py
trame/modules/__init__.py
trame/modules/annotations.py
trame/widgets/__init__.py
trame/widgets/annotations.py
trame_annotations/__init__.py
trame_annotations/module/.gitignore
trame_annotations/module/__init__.py
trame_annotations/module/serve/trame_annotations.umd.cjs
trame_annotations/module/serve/trame_annotations.umd.cjs.map
trame_annotations/widgets/__init__.py
trame_annotations/widgets/annotations.py
trame_annotations-0.5.0.dist-info/METADATA
trame_annotations-0.5.0.dist-info/WHEEL
trame_annotations-0.5.0.dist-info/licenses/LICENSE
trame_annotations-0.5.0.dist-info/RECORD
